{
    "fast_foods": [
        {
            "name": "Big Mac",
            "short_description": "Iconic double-decker burger with special sauce, lettuce, cheese, pickles, and onions on a sesame seed bun.",
            "estimated_price": 89850
        },
        {
            "name": "Spicy Chicken Sandwich",
            "short_description": "Crispy breaded chicken breast filet with spicy seasoning, mayo, and pickles on a toasted bun.",
            "estimated_price": 74850
        },
        {
            "name": "Fish Tacos",
            "short_description": "Battered fish strips with cabbage slaw, lime crema, and pico de gallo in soft corn tortillas.",
            "estimated_price": 119850
        },
        {
            "name": "Double Cheeseburger",
            "short_description": "Two beef patties with melted American cheese, pickles, onions, and condiments on a plain bun.",
            "estimated_price": 59850
        },
        {
            "name": "Chicken Nuggets (10pc)",
            "short_description": "Bite-sized pieces of breaded chicken breast served with choice of dipping sauce.",
            "estimated_price": 97350
        },
        {
            "name": "Supreme Pizza Slice",
            "short_description": "Large slice topped with pepperoni, sausage, bell peppers, onions, and mushrooms.",
            "estimated_price": 52500
        },
        {
            "name": "Burrito Bowl",
            "short_description": "Rice, beans, choice of meat, lettuce, cheese, and fresh salsa in a convenient bowl.",
            "estimated_price": 134850
        },
        {
            "name": "Classic Hot Dog",
            "short_description": "All-beef hot dog topped with mustard, ketchup, onions, and relish in a soft bun.",
            "estimated_price": 44850
        },
        {
            "name": "Chicken Wings (8pc)",
            "short_description": "Crispy wings tossed in buffalo sauce, served with celery and ranch dressing.",
            "estimated_price": 149850
        },
        {
            "name": "French Fries",
            "short_description": "Golden-brown potato fries, perfectly seasoned with salt and served hot and crispy.",
            "estimated_price": 37350
        },
        {
            "name": "Veggie Wrap",
            "short_description": "Fresh vegetables, hummus, and feta cheese wrapped in a spinach tortilla.",
            "estimated_price": 104850
        },
        {
            "name": "Chicken Caesar Salad",
            "short_description": "Grilled chicken breast over romaine lettuce with parmesan, croutons, and Caesar dressing.",
            "estimated_price": 119850
        },
        {
            "name": "Philly Cheesesteak",
            "short_description": "Thinly sliced beef with melted cheese, grilled onions, and peppers on a hoagie roll.",
            "estimated_price": 127350
        },
        {
            "name": "Onion Rings",
            "short_description": "Thick-cut onions battered and fried until golden, served with dipping sauce.",
            "estimated_price": 59850
        },
        {
            "name": "Ice Cream Sundae",
            "short_description": "Vanilla soft-serve topped with hot fudge, whipped cream, nuts, and a cherry.",
            "estimated_price": 67350
        }
    ]
}